{"0": "addvers", "1": "areyoulo", "2": "bay", "3": "betarbiat", "4": "buti", "5": "changizoff", "6": "comtopv", "7": "danger", "8": "dardbedarmon", "9": "dieforyoy", "10": "dontsend", "11": "drags", "12": "eted", "13": "gav", "14": "go", "15": "gomsho", "16": "goodmorning", "17": "gotoheal", "18": "gozzo", "19": "havaal", "20": "haw_are_you", "21": "hi", "22": "his", "23": "hoselatonadaram", "24": "howiscreator", "25": "i_hite_you", "26": "icom", "27": "im_good", "28": "im_sad", "29": "imsadbetch", "30": "ineedtites", "31": "itsyou", "32": "iwanted", "33": "khaaaar", "34": "khafesho", "35": "khaktosaret", "36": "kiss", "37": "koft", "38": "left", "39": "like_me", "40": "love", "41": "lovly", "42": "marreme", "43": "merc", "44": "miss", "45": "mother_fuck", "46": "no", "47": "not_buti", "48": "oooof", "49": "orjins", "50": "oskool", "51": "quiet", "52": "rootcerasham", "53": "sheet", "54": "spiet", "55": "very_nice", "56": "war", "57": "waw", "58": "whatsapp", "59": "whatyousay", "60": "zahr", "61": "zesht"}